task1/lfsr.sv
module lfsr (
    input logic clk,
    input logic rst,
    output logic [6:0] data_out,
    input logic en
);

logic [7:1] sreg;

always_ff @ (posedge clk)
    if (rst)
        sreg <= 7'b1;
    else if(en)
        sreg <= {sreg[6:1], sreg[3]^sreg[7]};

assign data_out = sreg; 
endmodule

task1/lfsr.vcd
$version Generated by VerilatedVcd $end
$date Thu Nov  3 09:30:03 2022 $end
$timescale 1ps $end

 $scope module TOP $end
  $var wire  1 # clk $end
  $var wire  7 % data_out [6:0] $end
  $var wire  1 & en $end
  $var wire  1 $ rst $end
  $scope module lfsr $end
   $var wire  1 # clk $end
   $var wire  7 % data_out [6:0] $end
   $var wire  1 & en $end
   $var wire  1 $ rst $end
   $var wire  7 ' sreg [7:1] $end
  $upscope $end
 $upscope $end
$enddefinitions $end


#0
0#
0$
b0000000 %
0&
b0000000 '
#1
1#
#2
0#
1$
#3
1#
b0000001 %
b0000001 '
#4
0#
#5
1#
#6
0#
0$
#7
1#
#8
0#
#9
1#
#10
0#
#11
1#
#12
0#
#13
1#
#14
0#
#15
1#
#16
0#
#17
1#
#18
0#
#19
1#
#20
0#
#21
1#
#22
0#
#23
1#
#24
0#
#25
1#
#26
0#
#27
1#
#28
0#
#29
1#
#30
0#
#31
1#
#32
0#
#33
1#
#34
0#
#35
1#
#36
0#
#37
1#
#38
0#
#39
1#
#40
0#
#41
1#
#42
0#
#43
1#
#44
0#
#45
1#
#46
0#
#47
1#
#48
0#
#49
1#
#50
0#
#51
1#
#52
0#
#53
1#
#54
0#
#55
1#
#56
0#
#57
1#
#58
0#
#59
1#
#60
0#
1&
#61
1#
b0000010 %
b0000010 '
#62
0#
0&
#63
1#
#64
0#
#65
1#
#66
0#
#67
1#
#68
0#
#69
1#
#70
0#
#71
1#
#72
0#
#73
1#
#74
0#
#75
1#
#76
0#
#77
1#
#78
0#
#79
1#
#80
0#
#81
1#
#82
0#
#83
1#
#84
0#
#85
1#
#86
0#
1&
#87
1#
b0000100 %
b0000100 '
#88
0#
0&
#89
1#
#90
0#
#91
1#
#92
0#
#93
1#
#94
0#
#95
1#
#96
0#
#97
1#
#98
0#
#99
1#
#100
0#
#101
1#
#102
0#
#103
1#
#104
0#
#105
1#
#106
0#
#107
1#
#108
0#
#109
1#
#110
0#
#111
1#
#112
0#
1&
#113
1#
b0001001 %
b0001001 '
#114
0#
0&
